iotile_analytics/__init__.py
iotile_analytics/core/__init__.py
iotile_analytics/core/environment.py
iotile_analytics/core/exceptions.py
iotile_analytics/core/group.py
iotile_analytics/core/session.py
iotile_analytics/core/stream_series.py
iotile_analytics/core/channels/__init__.py
iotile_analytics/core/channels/channel.py
iotile_analytics/core/channels/cloud_api.py
iotile_analytics/core/interaction/__init__.py
iotile_analytics/core/interaction/progress.py
iotile_analytics/core/utilities/__init__.py
iotile_analytics/core/utilities/aggregator.py
iotile_analytics/core/utilities/domain.py
iotile_analytics/core/utilities/envelope.py
iotile_analytics/core/utilities/url_routines.py
iotile_analytics_core-0.6.1.dist-info/LICENSE.md
iotile_analytics_core-0.6.1.dist-info/METADATA
iotile_analytics_core-0.6.1.dist-info/WHEEL
iotile_analytics_core-0.6.1.dist-info/top_level.txt
iotile_analytics_core-0.6.1.dist-info/RECORD
