Metadata-Version: 2.1
Name: iotile-analytics-core
Version: 0.6.1
Summary: A data science bridge for iotile.cloud
Home-page: https://github.com/iotile/typedargs
Author: Arch
Author-email: info@arch-iot.com
License: LGPLv3
Platform: UNKNOWN
Classifier: Programming Language :: Python
Classifier: Programming Language :: Python :: 2
Classifier: Programming Language :: Python :: 2.7
Classifier: Programming Language :: Python :: 3
Classifier: Programming Language :: Python :: 3.5
Classifier: Programming Language :: Python :: 3.6
Classifier: Development Status :: 3 - Alpha
Classifier: License :: OSI Approved :: GNU Library or Lesser General Public License (LGPL)
Classifier: Operating System :: OS Independent
Classifier: Topic :: Software Development :: Libraries :: Python Modules
Requires-Dist: future (>=0.16.0)
Requires-Dist: numpy (>=1.13.1)
Requires-Dist: pandas (>=0.20.3)
Requires-Dist: scipy (>=1.0.0)
Requires-Dist: typedargs (>=0.10.0)
Requires-Dist: iotile-cloud (>=0.9.2)
Requires-Dist: tqdm (>=4.19.4)
